LICENSE
README.md
setup.py
sosiska/__init__.py
sosiska/__main__.py
sosiska.egg-info/PKG-INFO
sosiska.egg-info/SOURCES.txt
sosiska.egg-info/dependency_links.txt
sosiska.egg-info/requires.txt
sosiska.egg-info/top_level.txt